cloudhealth/__init__.py
cloudhealth/assets.py
cloudhealth/awsaccounts.py
cloudhealth/client.py
cloudhealth/exceptions.py
cloudhealth/metrics.py
cloudhealth/organization.py
cloudhealth/partner.py
cloudhealth/perspectives.py
cloudhealth/policies.py
cloudhealth/reports.py
cloudhealth/sso.py
cloudhealth/tags.py
cloudhealth/utils.py
cloudhealth_client-0.5.0.dist-info/LICENSE
cloudhealth_client-0.5.0.dist-info/METADATA
cloudhealth_client-0.5.0.dist-info/WHEEL
cloudhealth_client-0.5.0.dist-info/top_level.txt
cloudhealth_client-0.5.0.dist-info/RECORD
