Metadata-Version: 2.1
Name: cloudhealth-client
Version: 0.5.0
Summary: A REST Client for Cloudhealth
Home-page: https://github.com/albertonarro/cloudhealth-client
Author: Alberto Narro
Author-email: alberto.narro@hotmail.com
License: Apache-2.0
Keywords: cloudhealth,client,cli
Classifier: License :: OSI Approved :: Apache Software License
Classifier: Programming Language :: Python :: 3
Requires-Python: >=3.7
License-File: LICENSE
Requires-Dist: requests (==2.28.2)
